{"project_solution_admin.md":"fd1924e9","framework_nuxt.md":"7a24e168","framework_test.md":"76e5d913","framework_vue-router.md":"34326ab6","framework_vuex.md":"2839e50d","index.md":"7bca29f5","project_build_nobundle.md":"5e1f29b8","project_build_update.md":"9498be19","project_deploy_grey-publish.md":"cfc4e0c2","project_deploy_index.md":"9f2400da","project_deploy_publish-rollback.md":"832a81b5","project_deploy_publish.md":"4db4ec67","project_deploy_registry.md":"5ccec82a","project_index.md":"27851a0b","project_module.md":"afcdcd58","project_solution_component-library.md":"da07a0bb","project_standard_index.md":"b44b41e5","project_solution_material.md":"f95faacd","project_standard_git.md":"5bbf73b1","web_foundation_asynchronous.md":"6b36ffeb","web_browser_task.md":"901c37f5","project_standard_project-process.md":"528cbba2","project_tools_npm.md":"8f46da47","web_browser_chrome.md":"86dfd0b7","project_tools_cli.md":"655ef3a1","web_foundation_cross-domain.md":"4736126c","web_js_javascript-datatype.md":"8a6e9230","web_js_javascript-optimization.md":"e935984f","web_js_javascript-prototype.md":"4473d131","web_other_blog.md":"2e335c59","web_other_share.md":"040c08b1","project_tools_index.md":"c032417a","web_js_call-apply-bind.md":"d49d941e","web_foundation_index.md":"ebb0d5a6","web_foundation_functional.md":"bdd21b97","web_foundation_ecmascript.md":"c9e6ab23","web_other_essay.md":"9ed9b759","project_tools_webpack.md":"cf3a11bd","web_js_extends.md":"3aa2005d"}
