{"framework_react-css-in-js.md":"ed810208","framework_react-hooks.md":"3a2954e5","framework_react-ecology.md":"ae024a24","framework_nuxt.md":"bc0bb4eb","framework_react-component.md":"c5b29650","framework_react-fiber.md":"ca57088d","project_tools_yarn.md":"4a98d22c","web_browser_chrome.md":"4a74fecf","web_browser_task.md":"858c9181","web_foundation_asynchronous.md":"9c75e407","web_foundation_cross-domain.md":"74481bba","web_foundation_ecmascript.md":"8ef8a7c4","web_foundation_engineer.md":"c64003f6","web_foundation_functional.md":"6884931b","web_foundation_index.md":"895e7c7e","project_tools_webpack.md":"5c6703a0","web_js_javascript-optimization.md":"5d789a6f","web_js_javascript-datatype.md":"5727e656","web_js_javascript-prototype.md":"e9b5bda4","web_node_index.md":"b787cc07","web_js_json.md":"018b86fa","web_other_blog.md":"e356b946","web_other_essay.md":"3954c24b","web_other_share.md":"aba03342","web_node_koa.md":"f043d6ba","framework_vue-pinia.md":"fa0e0bbc","framework_vue-compiler-component.md":"6e94934e","framework_vue-loader.md":"2abe0348","framework_vue-router.md":"5c7eef2f","framework_vue-ssr.md":"da07a3aa","framework_react.md":"cd23d51e","framework_vue3.md":"08e1cc95","project_build_update.md":"20cc2c24","project_build_automation.md":"960b0fd3","project_build_nobundle.md":"b9181612","project_build_ssr.md":"6734a230","project_deploy_index.md":"e1b574ed","project_deploy_publish-rollback.md":"9586df7e","project_deploy_publish.md":"bc530e43","project_deploy_registry.md":"53c770e4","project_deploy_ci.md":"8471dc1f","project_deploy_grey-publish.md":"29fe6dbf","project_component.md":"67c9bafe","project_index.md":"68283385","project_solution_concurrent-download.md":"797f01d5","project_solution_file-upload.md":"daa36d2d","project_plugin.md":"7de73d1a","project_solution_component-library.md":"afd3c71d","project_solution_watermark.md":"50637315","project_standard_index.md":"60c967d6","project_solution_material.md":"1fe53e77","project_solution_plan.md":"0dfcb695","project_solution_resume-online.md":"cec42b1e","project_solution_statistics.md":"18fa2d45","project_tools_gridsome.md":"82b29db0","project_structure.md":"eb8280ae","project_tools_cli.md":"bb3f741d","project_tools_docs.md":"d3cac5c9","project_standard_project-process.md":"79815100","project_tools_pnpm.md":"1687cb76","project_tools_mock.md":"767bf280","project_tools_index.md":"a021bb46","project_module.md":"ef5efa72","project_tools_webpack-source.md":"e9df75ff","project_tools_vite.md":"a54b026f","framework_react-mobx6.md":"d7fddf6a","project_standard_git.md":"8466aca4","project_tools_npm.md":"13baffad","web_foundation_typescript.md":"000d5dc0","framework_vuex.md":"51c300d8","web_js_ast.md":"1776c12f","web_js_call-apply-bind.md":"5b67d0aa","framework_react-source.md":"0fc9d8b5","framework_react-vdom.md":"6e0f2a19","index.md":"c408279c","web_js_copy.md":"47680337","framework_vue-vdom.md":"acf4fe32","framework_vue-reactivity.md":"ece1e08f","web_js_extends.md":"b3318f82","web_js_closure.md":"9a14953f"}
